tswidgets/__init__.py
tswidgets/utils.py
tswidgets/datasets/__init__.py
tswidgets/datasets/enders.pkl
tswidgets/datasets/hyndman.pkl
tswidgets/datasets/levendis.pkl
tswidgets/datasets/load_dataset.py
tswidgets-0.0.2.dist-info/METADATA
tswidgets-0.0.2.dist-info/WHEEL
tswidgets-0.0.2.dist-info/top_level.txt
tswidgets-0.0.2.dist-info/RECORD
