Metadata-Version: 2.1
Name: tswidgets
Version: 0.0.2
Summary: Some functions and datasets to work with time series
License: BSD
Requires-Dist: matplotlib ==3.7.5
Requires-Dist: numpy ==1.24.4
Requires-Dist: pandas ==2.0.3
Requires-Dist: Requests ==2.32.3
Requires-Dist: seaborn ==0.13.2
Requires-Dist: setuptools ==69.2.0
Requires-Dist: statsmodels ==0.14.1
